{
  "kind": "collectionType",
  "collectionName": "authors",
  "info": {
    "singularName": "author",
    "pluralName": "authors",
    "displayName": "Author"
  },
  "options": {
    "draftAndPublish": true
  },
  "pluginOptions": {},
  "attributes": {
    "display_name": {
      "type": "string"
    },
    "bio": {
      "type": "text"
    },
    "avatar": {
      "type": "media",
      "multiple": false,
      "allowedTypes": [
        "images",
        "files",
        "videos",
        "audios"
      ]
    },
    "admin_user": {
      "type": "relation",
      "relation": "oneToOne",
      "target": "admin::user"
    },
    "temple_posts": {
      "type": "relation",
      "relation": "oneToMany",
      "target": "api::temple-post.temple-post",
      "mappedBy": "author"
    }
  }
}
